rbac_utils/__init__.py
rbac_utils/utils.py
rbac_utils-1.0.1.dist-info/METADATA
rbac_utils-1.0.1.dist-info/WHEEL
rbac_utils-1.0.1.dist-info/top_level.txt
rbac_utils-1.0.1.dist-info/RECORD
