Metadata-Version: 2.1
Name: rbac-utils
Version: 1.0.1
Summary: Utilities for RBAC system
Home-page: https://bitbucket.org/lendenite/ldc_packages/src/master/
Author: Sandeep Sharma
Author-email: sandeep.sharma@lendenclub.com
License: UNKNOWN
Platform: UNKNOWN
Classifier: Intended Audience :: Developers
Classifier: Programming Language :: Python :: 3.8
Requires-Dist: PyJWT >=2.7.0
Requires-Dist: requests >=2.18.4
Requires-Dist: python-dotenv >=1.0.0
